ontbo/__init__.py
ontbo/i_ontbo_server.py
ontbo/ontbo.py
ontbo/profile.py
ontbo/query_type.py
ontbo/scene.py
ontbo/scene_message.py
ontbo/update_status.py
ontbo-1.3.1.251003.dist-info/METADATA
ontbo-1.3.1.251003.dist-info/WHEEL
ontbo-1.3.1.251003.dist-info/licenses/LICENSE
ontbo-1.3.1.251003.dist-info/RECORD
