Metadata-Version: 2.4
Name: ontbo
Version: 1.3.1.251003
Summary: Python client for the Ontbo API. Go-to https://www.ontbo.com/.
Project-URL: Homepage, https://github.com/Ontbo/ontbo-context-api
Project-URL: Issues, https://github.com/Ontbo/ontbo-context-api/issues
Author-email: Stéphane Aubry <contact@ontbo.com>
License:                                  Apache License
License-File: LICENSE
Requires-Dist: requests
